genysis/__init__.py
genysis/client.py
genysis/legacy/__init__.py
genysis/legacy/adaptiveLattice.py
genysis/legacy/genysis.py
genysis/legacy/mesh.py
genysis/legacy/meshRepair.py
genysis/legacy/meshRepair_v2.py
genysis/legacy/parse_request.py
genysis_staging-0.0.8.dist-info/DESCRIPTION.rst
genysis_staging-0.0.8.dist-info/METADATA
genysis_staging-0.0.8.dist-info/RECORD
genysis_staging-0.0.8.dist-info/WHEEL
genysis_staging-0.0.8.dist-info/metadata.json
genysis_staging-0.0.8.dist-info/top_level.txt
