Metadata-Version: 2.0
Name: genysis-staging
Version: 0.0.8
Summary: generative design
Home-page: UNKNOWN
Author: Li
Author-email: UNKNOWN
License: MIT
Platform: UNKNOWN
